django_browserless/__init__.py
django_browserless/apps.py
django_browserless/auth/__init__.py
django_browserless/auth/authenticators.py
django_browserless/auth/stores.py
django_browserless/checks.py
django_browserless/client.py
django_browserless/conftest.py
django_browserless/entities.py
django_browserless/forms.py
django_browserless/pdf.py
django_browserless/serializers.py
django_browserless/settings.py
django_browserless/views/__init__.py
django_browserless/views/django_views.py
django_browserless/views/drf_views.py
django_browserless/views/response.py
django_browserless-0.1.1.dist-info/LICENSE
django_browserless-0.1.1.dist-info/METADATA
django_browserless-0.1.1.dist-info/WHEEL
django_browserless-0.1.1.dist-info/RECORD
