Metadata-Version: 2.1
Name: django-browserless
Version: 0.1.1
Summary: Genreate PDFs from URLs using browserless
License: MIT
Author: Sylvain Gable
Author-email: sylvain@vingtcinq.io
Requires-Python: >=3.8,<4.0
Classifier: License :: OSI Approved :: MIT License
Classifier: Programming Language :: Python :: 3
Classifier: Programming Language :: Python :: 3.8
Classifier: Programming Language :: Python :: 3.9
Classifier: Programming Language :: Python :: 3.10
Classifier: Programming Language :: Python :: 3.11
Classifier: Programming Language :: Python :: 3.12
Requires-Dist: Django (>=4.2,<5.0)
Requires-Dist: attrs (>=23.2.0,<24.0.0)
Requires-Dist: djangorestframework (>=3.12.0,<4.0.0)
Requires-Dist: httpx (>=0.27.0,<0.28.0)
